simple_file_splitters/__init__.py
simple_file_splitters/splitters.py
simple_file_splitters-0.0.2.dist-info/LICENSE.txt
simple_file_splitters-0.0.2.dist-info/METADATA
simple_file_splitters-0.0.2.dist-info/WHEEL
simple_file_splitters-0.0.2.dist-info/top_level.txt
simple_file_splitters-0.0.2.dist-info/RECORD
